[
    {
        "id": "police_station_1",
        "x_coordinate": 41.66,
        "y_coordinate": -0.8605,
        "officers_on_duty": 12,
        "specialties": [
            "patrol",
            "crime prevention",
            "investigation"
        ],
        "status": "operational"
    },
    {
        "id": "police_station_2",
        "x_coordinate": 41.661,
        "y_coordinate": -0.8608,
        "officers_on_duty": 8,
        "specialties": [
            "patrol",
            "investigation"
        ],
        "status": "operational"
    }
]